ward_labels_upload/__init__.py
ward_labels_upload/config.py
ward_labels_upload/domain.py
ward_labels_upload/upload.py
ward_labels_upload/utils.py
ward_labels_upload-0.0.10.dist-info/LICENSE
ward_labels_upload-0.0.10.dist-info/METADATA
ward_labels_upload-0.0.10.dist-info/WHEEL
ward_labels_upload-0.0.10.dist-info/top_level.txt
ward_labels_upload-0.0.10.dist-info/RECORD
